projector_installer/LICENSE.txt
projector_installer/__init__.py
projector_installer/actions.py
projector_installer/apps.py
projector_installer/certificate_chain.py
projector_installer/cmd.py
projector_installer/compatible_ide.json
projector_installer/config_generator.py
projector_installer/defaults.py
projector_installer/dialogs.py
projector_installer/global_config.py
projector_installer/ide_update.py
projector_installer/license.py
projector_installer/log_utils.py
projector_installer/products.py
projector_installer/projector_updates.py
projector_installer/run_config.py
projector_installer/secure_config.py
projector_installer/timeout.py
projector_installer/utils.py
projector_installer/version.py
projector_installer/bundled/server/Java-WebSocket-1.5.2.jar
projector_installer/bundled/server/annotations-13.0.jar
projector_installer/bundled/server/dnsjava-3.4.3.jar
projector_installer/bundled/server/javassist-3.28.0-GA.jar
projector_installer/bundled/server/jsoup-1.14.3.jar
projector_installer/bundled/server/kotlin-reflect-1.6.10.jar
projector_installer/bundled/server/kotlin-stdlib-1.6.10.jar
projector_installer/bundled/server/kotlin-stdlib-common-1.6.10.jar
projector_installer/bundled/server/kotlin-stdlib-jdk7-1.6.10.jar
projector_installer/bundled/server/kotlin-stdlib-jdk8-1.6.10.jar
projector_installer/bundled/server/kotlinx-coroutines-core-jvm-1.6.0.jar
projector_installer/bundled/server/kotlinx-serialization-core-jvm-1.3.1.jar
projector_installer/bundled/server/kotlinx-serialization-json-jvm-1.3.1.jar
projector_installer/bundled/server/kotlinx-serialization-protobuf-jvm-1.3.1.jar
projector_installer/bundled/server/projector-awt-1.8.1.jar
projector_installer/bundled/server/projector-awt-common-1.8.1.jar
projector_installer/bundled/server/projector-common-jvm-803c9a4b.jar
projector_installer/bundled/server/projector-ij-common-803c9a4b.jar
projector_installer/bundled/server/projector-server-1.8.1.jar
projector_installer/bundled/server/projector-server-common-1.8.1.jar
projector_installer-1.8.0.dist-info/LICENSE.txt
projector_installer-1.8.0.dist-info/METADATA
projector_installer-1.8.0.dist-info/WHEEL
projector_installer-1.8.0.dist-info/entry_points.txt
projector_installer-1.8.0.dist-info/top_level.txt
projector_installer-1.8.0.dist-info/RECORD
