Metadata-Version: 2.1
Name: projector-installer
Version: 1.8.0
Summary: Install, configure and run JetBrains IDEs with Projector Server on Linux or in WSL
Home-page: https://github.com/JetBrains/projector-installer
Author: JetBrains
Author-email: sergey.bulgakov@jetbrains.com
Maintainer: JetBrains
License: UNKNOWN
Project-URL: Projector source, https://github.com/JetBrains/projector-installer
Project-URL: Projector documentation, https://github.com/JetBrains/projector-installer
Platform: UNKNOWN
Classifier: Intended Audience :: Developers
Classifier: License :: OSI Approved :: Apache Software License
Classifier: Natural Language :: English
Classifier: Operating System :: POSIX
Classifier: Operating System :: POSIX :: Linux
Classifier: Operating System :: POSIX :: BSD
Classifier: Programming Language :: Python
Classifier: Programming Language :: Python :: 3
Classifier: Programming Language :: Python :: 3 :: Only
Classifier: Programming Language :: Python :: 3.6
Classifier: Programming Language :: Python :: 3.7
Classifier: Programming Language :: Python :: 3.8
Classifier: Programming Language :: Python :: Implementation :: CPython
Requires-Python: >=3.6
Requires-Dist: wheel
Requires-Dist: click
Requires-Dist: netifaces
Requires-Dist: setuptools
Requires-Dist: cryptography
Requires-Dist: pyOpenSSL
Requires-Dist: pip
Requires-Dist: dataclasses
